pywassap/.DS_Store
pywassap/__init__.py
pywassap/_main.py
pywassap-0.0.2.dist-info/LICENSE
pywassap-0.0.2.dist-info/WHEEL
pywassap-0.0.2.dist-info/METADATA
pywassap-0.0.2.dist-info/RECORD
