Metadata-Version: 2.1
Name: pywassap
Version: 0.0.2
Summary: PyWassap is a python library for sending WhatsApp messages using the WhatsApp Business API.
Home-page: https://github.com/Aarif1430/pywassap
License: MIT
Author: Aarif Malik
Author-email: malikarif13@gmail.com
Requires-Python: >=3.10,<4.0
Classifier: Development Status :: 4 - Beta
Classifier: Framework :: AsyncIO
Classifier: Framework :: Trio
Classifier: Intended Audience :: Developers
Classifier: Intended Audience :: Education
Classifier: Intended Audience :: Information Technology
Classifier: Intended Audience :: Science/Research
Classifier: Intended Audience :: System Administrators
Classifier: License :: OSI Approved :: MIT License
Classifier: Programming Language :: Python :: 3
Classifier: Programming Language :: Python :: 3.10
Classifier: Programming Language :: Python :: 3.11
Classifier: Programming Language :: Python :: 3 :: Only
Classifier: Programming Language :: Python :: 3.10
Classifier: Programming Language :: Python :: 3.9
Classifier: Topic :: Internet
Classifier: Typing :: Typed
Requires-Dist: aiohttp (>=3.8.3,<4.0.0)
Project-URL: Documentation, https://pywassap.netlify.app/
Project-URL: Repository, https://github.com/Aarif1430/pywassap
